slack_cleaner2/__init__.py
slack_cleaner2/__main__.py
slack_cleaner2/_info.py
slack_cleaner2/cli.py
slack_cleaner2/logger.py
slack_cleaner2/model.py
slack_cleaner2/predicates.py
slack_cleaner2/util.py
slack_cleaner2-3.2.7.dist-info/LICENSE
slack_cleaner2-3.2.7.dist-info/METADATA
slack_cleaner2-3.2.7.dist-info/WHEEL
slack_cleaner2-3.2.7.dist-info/entry_points.txt
slack_cleaner2-3.2.7.dist-info/top_level.txt
slack_cleaner2-3.2.7.dist-info/RECORD
