Metadata-Version: 2.1
Name: slack-cleaner2
Version: 3.2.7
Summary: Slack Cleaner2 is an improved slack cleaner version using a python first approach
Home-page: https://github.com/sgratzl/slack_cleaner2
Author: Samuel Gratzl
Author-email: sam@sgratzl.com
License: MIT license
Keywords: slack_cleaner2 slack slack-cleaner
Classifier: Development Status :: 5 - Production/Stable
Classifier: Intended Audience :: Developers
Classifier: License :: OSI Approved :: MIT License
Classifier: Natural Language :: English
Classifier: Programming Language :: Python :: 3.8
Classifier: Programming Language :: Python :: 3.9
Classifier: Programming Language :: Python :: 3.10
License-File: LICENSE
Requires-Dist: slack-sdk (>=3.13.0)
Requires-Dist: colorama (>=0.4.4)
Requires-Dist: python-dateutil (>=2.8.0)
Requires-Dist: requests (>=2.26.0)
